assembly/__init__.py
autogator/__init__.py
autogator/analysis.py
autogator/api.py
autogator/circuits.py
autogator/controllers.py
autogator/errors.py
autogator/experiments.py
autogator/hardware.py
autogator/profiles.py
autogator/routines.py
AutoGator-0.3.0.dist-info/LICENSE
AutoGator-0.3.0.dist-info/METADATA
AutoGator-0.3.0.dist-info/WHEEL
AutoGator-0.3.0.dist-info/top_level.txt
AutoGator-0.3.0.dist-info/RECORD
