Metadata-Version: 2.1
Name: AutoGator
Version: 0.3.0
Summary: A software package for camera-assisted motion control of PIC chip interrogation platforms.
Home-page: https://github.com/BYUCamachoLab/autogator
Author: Sequoia Ploeg
Author-email: sequoia.ploeg@byu.edu
License: MIT
Project-URL: Source, https://github.com/BYUCamachoLab/autogator
Project-URL: Tracker, https://github.com/BYUCamachoLab/autogator/issues
Project-URL: Research Group, https://camacholab.byu.edu/
Keywords: PyroLab,Pyro5,Pyro,lab,instrument,remote,resources,framework,laboratory,instrumentation,hardware,science,remote,network,integration,PIC,photonic integrated circuit
Platform: Windows
Platform: Linux
Platform: Mac OS-X
Classifier: Development Status :: 4 - Beta
Classifier: Intended Audience :: Science/Research
Classifier: Intended Audience :: Education
Classifier: License :: OSI Approved :: GNU General Public License v3 or later (GPLv3+)
Classifier: Operating System :: Microsoft :: Windows
Classifier: Operating System :: MacOS
Classifier: Operating System :: POSIX :: Linux
Classifier: Operating System :: OS Independent
Classifier: Programming Language :: Python :: 3
Classifier: Programming Language :: Python :: 3.7
Classifier: Programming Language :: Python :: 3.8
Classifier: Programming Language :: Python :: 3.9
Classifier: Programming Language :: Python :: 3.10
Classifier: Programming Language :: Python :: 3 :: Only
Classifier: Programming Language :: Python :: Implementation :: CPython
Classifier: Topic :: Scientific/Engineering
Classifier: Topic :: Scientific/Engineering :: Physics
Classifier: Topic :: Scientific/Engineering :: Visualization
Classifier: Topic :: Software Development :: Libraries :: Python Modules
Requires-Python: >=3.7
License-File: LICENSE
Requires-Dist: numpy
Requires-Dist: scipy
Requires-Dist: matplotlib
Requires-Dist: appdirs
Requires-Dist: keyboard
Requires-Dist: pydantic
Requires-Dist: pyrolab
